README.rst
setup.py
computer_communication_framework/__init__.py
computer_communication_framework/base_cluster_submissions.py
computer_communication_framework/base_connection.py
computer_communication_framework/base_mga.py
computer_communication_framework/batch_jobs.py
computer_communication_framework/test.py
computer_communication_framework.egg-info/PKG-INFO
computer_communication_framework.egg-info/SOURCES.txt
computer_communication_framework.egg-info/dependency_links.txt
computer_communication_framework.egg-info/top_level.txt
computer_communication_framework/examples/__init__.py
computer_communication_framework/examples/connections.py