Metadata-Version: 1.2
Name: computer-communication-framework
Version: 0.0.2
Summary: A quick and simple framework to develop proof-of-concept programs that use multiple computers.
Home-page: https://github.com/oliver-chalkley/computer_communication_framework
Author: Oliver Chalkley
Author-email: oliver.chalkley83@gmail.com
License: UNKNOWN
Keywords: remote computer control framework management communicate communication
Platform: UNKNOWN
Classifier: Development Status :: 2 - Pre-Alpha
Classifier: Intended Audience :: Science/Research
Classifier: Topic :: Software Development :: Libraries :: Application Frameworks
Classifier: License :: OSI Approved :: MIT License
Classifier: Programming Language :: Python :: 3
Classifier: Programming Language :: Python :: 3.4
Classifier: Programming Language :: Python :: 3.5
Classifier: Programming Language :: Python :: 3.6
Requires-Python: ~=3.0
